topmark/__init__.py
topmark/constants.py
topmark/file_resolver.py
topmark/py.typed
topmark/api/__init__.py
topmark/api/public_types.py
topmark/api/runtime.py
topmark/api/types.py
topmark/api/view.py
topmark/cli/__init__.py
topmark/cli/cli_types.py
topmark/cli/cmd_common.py
topmark/cli/config_resolver.py
topmark/cli/console.py
topmark/cli/console_helpers.py
topmark/cli/console_std.py
topmark/cli/errors.py
topmark/cli/io.py
topmark/cli/main.py
topmark/cli/options.py
topmark/cli/utils.py
topmark/cli/commands/__init__.py
topmark/cli/commands/check.py
topmark/cli/commands/config.py
topmark/cli/commands/config_defaults.py
topmark/cli/commands/config_dump.py
topmark/cli/commands/config_init.py
topmark/cli/commands/filetypes.py
topmark/cli/commands/processors.py
topmark/cli/commands/strip.py
topmark/cli/commands/version.py
topmark/cli_shared/__init__.py
topmark/cli_shared/console_api.py
topmark/cli_shared/machine_output.py
topmark/cli_shared/utils.py
topmark/config/__init__.py
topmark/config/io.py
topmark/config/logging.py
topmark/config/model.py
topmark/config/paths.py
topmark/config/policy.py
topmark/config/topmark-default.toml
topmark/config/types.py
topmark/core/diagnostics.py
topmark/core/enum_mixins.py
topmark/core/exit_codes.py
topmark/filetypes/__init__.py
topmark/filetypes/base.py
topmark/filetypes/instances.py
topmark/filetypes/policy.py
topmark/filetypes/registry.py
topmark/filetypes/builtins/__init__.py
topmark/filetypes/builtins/core_langs.py
topmark/filetypes/builtins/data.py
topmark/filetypes/builtins/docs.py
topmark/filetypes/builtins/ops.py
topmark/filetypes/builtins/scripting.py
topmark/filetypes/builtins/web.py
topmark/filetypes/checks/__init__.py
topmark/filetypes/checks/json_like.py
topmark/filetypes/checks/xml.py
topmark/filetypes/detectors/__init__.py
topmark/filetypes/detectors/jsonc.py
topmark/pipeline/__init__.py
topmark/pipeline/adapters.py
topmark/pipeline/engine.py
topmark/pipeline/hints.py
topmark/pipeline/pipelines.py
topmark-0.11.1.dist-info/licenses/LICENSE
topmark-0.11.1.dist-info/METADATA
topmark-0.11.1.dist-info/WHEEL
topmark-0.11.1.dist-info/entry_points.txt
topmark-0.11.1.dist-info/top_level.txt
topmark-0.11.1.dist-info/RECORD
