Metadata-Version: 2.4
Name: topmark
Version: 0.11.1
Summary: A Python CLI to inspect, validate, and manage license and copyright headers.
Author-email: Olivier Biot <olivier.biot@gmail.com>
License-Expression: MIT
Project-URL: Homepage, https://github.com/shutterfreak/topmark
Project-URL: Documentation, https://topmark.readthedocs.io/en/latest/
Project-URL: Source, https://github.com/shutterfreak/topmark
Project-URL: Changelog, https://github.com/shutterfreak/topmark/releases
Classifier: Programming Language :: Python :: 3.10
Classifier: Programming Language :: Python :: 3.11
Classifier: Programming Language :: Python :: 3.12
Classifier: Programming Language :: Python :: 3.13
Classifier: Programming Language :: Python :: 3.14
Classifier: Operating System :: OS Independent
Requires-Python: <3.15,>=3.10
License-File: LICENSE
Requires-Dist: pathspec<0.13.0,>=0.12.1
Requires-Dist: tomlkit<0.14.0,>=0.13.3
Requires-Dist: toml<0.11.0,>=0.10.2
Requires-Dist: yachalk<0.2.0,>=0.1.8
Requires-Dist: click<9.0.0,>=8.3.1
Provides-Extra: lock
Requires-Dist: pip-tools<8.0.0,>=7.5.2; extra == "lock"
Provides-Extra: dev
Requires-Dist: ruff<0.15.0,>=0.14.5; extra == "dev"
Requires-Dist: pydoclint<0.9.0,>=0.8.1; extra == "dev"
Requires-Dist: pylint<5.0.0,>=4.0.3; extra == "dev"
Requires-Dist: pyright<1.2.0,>=1.1.407; extra == "dev"
Requires-Dist: mdformat<2.0.0,>=1.0.0; extra == "dev"
Requires-Dist: mdformat-gfm<2.0.0,>=1.0.0; extra == "dev"
Requires-Dist: taplo<0.10.0,>=0.9.3; extra == "dev"
Requires-Dist: pre-commit<5.0.0,>=4.4.0; extra == "dev"
Requires-Dist: nox<2026.0.0,>=2025.11.12; extra == "dev"
Requires-Dist: nox-uv<1.0.0,>=0.7.0; extra == "dev"
Requires-Dist: uv<0.6.0,>=0.5.0; extra == "dev"
Requires-Dist: build<2.0.0,>=1.3.0; extra == "dev"
Requires-Dist: twine<7.0.0,>=6.2.0; extra == "dev"
Requires-Dist: typing-extensions<5.0.0,>=4.15.0; extra == "dev"
Requires-Dist: mbake<2.0.0,>=1.4.3; extra == "dev"
Provides-Extra: docs
Requires-Dist: mkdocs<2.0.0,>=1.6.1; extra == "docs"
Requires-Dist: mkdocs-material<10.0.0,>=9.7.0; extra == "docs"
Requires-Dist: mkdocstrings[python]<0.31.0,>=0.30.1; extra == "docs"
Requires-Dist: mkdocs-autorefs<2.0.0,>=1.4.3; extra == "docs"
Requires-Dist: mkdocs-include-markdown-plugin<8.0.0,>=7.2.0; extra == "docs"
Requires-Dist: pymdown-extensions<11.0.0,>=10.17.1; extra == "docs"
Requires-Dist: mkdocs-gen-files<0.7.0,>=0.5.0; extra == "docs"
Requires-Dist: mkdocs-simple-hooks<0.2.0,>=0.1.5; extra == "docs"
Requires-Dist: ruff<0.15.0,>=0.14.5; extra == "docs"
Requires-Dist: typing-extensions<5.0.0,>=4.15.0; extra == "docs"
Provides-Extra: test
Requires-Dist: pytest<10.0.0,>=9.0.1; extra == "test"
Requires-Dist: pytest-xdist<4.0.0,>=3.8.0; extra == "test"
Requires-Dist: hypothesis<7.0.0,>=6.148.2; extra == "test"
Provides-Extra: typing
Requires-Dist: types-toml<0.11.0,>=0.10.8.20240310; extra == "typing"
Dynamic: license-file
